{
    "root": {
        "node_id": 0,
        "feature_index": 38,
        "threshold": 0.5,
        "num_samples": 54320,
        "removed_features": [],
        "left": {
            "node_id": 2,
            "feature_index": 13,
            "threshold": 0.5,
            "num_samples": 46260,
            "removed_features": [],
            "left": {
                "node_id": 4,
                "feature_index": 37,
                "threshold": 0.5,
                "num_samples": 38234,
                "removed_features": [],
                "left": {
                    "node_id": 6,
                    "feature_index": 27,
                    "threshold": 0.5,
                    "num_samples": 30269,
                    "removed_features": [],
                    "left": {
                        "node_id": 12,
                        "feature_index": 29,
                        "threshold": 0.5,
                        "num_samples": 22338,
                        "removed_features": [],
                        "left": {
                            "node_id": 16,
                            "feature_index": 16,
                            "threshold": 0.5,
                            "num_samples": 18310,
                            "removed_features": [],
                            "left": {
                                "node_id": 32,
                                "feature_index": 32,
                                "threshold": 0.5,
                                "num_samples": 14348,
                                "removed_features": [],
                                "left": {
                                    "node_id": 34,
                                    "feature_index": 33,
                                    "threshold": 0.5,
                                    "num_samples": 12343,
                                    "removed_features": [],
                                    "left": {
                                        "node_id": 36,
                                        "feature_index": 30,
                                        "threshold": 0.5,
                                        "num_samples": 10234,
                                        "removed_features": [],
                                        "left": {
                                            "node_id": 38,
                                            "feature_index": 31,
                                            "threshold": 0.5,
                                            "num_samples": 8228,
                                            "removed_features": [],
                                            "left": {
                                                "node_id": 56,
                                                "feature_index": 35,
                                                "threshold": 0.5,
                                                "num_samples": 8142,
                                                "removed_features": [],
                                                "left": {
                                                    "node_id": 60,
                                                    "feature_index": 34,
                                                    "threshold": 0.5,
                                                    "num_samples": 8101,
                                                    "removed_features": [],
                                                    "left": {
                                                        "node_id": 64,
                                                        "feature_index": null,
                                                        "threshold": null,
                                                        "num_samples": 8061,
                                                        "removed_features": [],
                                                        "left": null,
                                                        "right": null,
                                                        "output": 4,
                                                        "depth": 12
                                                    },
                                                    "right": {
                                                        "node_id": 61,
                                                        "feature_index": 41,
                                                        "threshold": 0.5,
                                                        "num_samples": 40,
                                                        "removed_features": [],
                                                        "left": {
                                                            "node_id": 63,
                                                            "feature_index": null,
                                                            "threshold": null,
                                                            "num_samples": 18,
                                                            "removed_features": [],
                                                            "left": null,
                                                            "right": null,
                                                            "output": 5,
                                                            "depth": 13
                                                        },
                                                        "right": {
                                                            "node_id": 62,
                                                            "feature_index": null,
                                                            "threshold": null,
                                                            "num_samples": 22,
                                                            "removed_features": [],
                                                            "left": null,
                                                            "right": null,
                                                            "output": 6,
                                                            "depth": 13
                                                        },
                                                        "output": null,
                                                        "depth": 12
                                                    },
                                                    "output": null,
                                                    "depth": 11
                                                },
                                                "right": {
                                                    "node_id": 57,
                                                    "feature_index": 41,
                                                    "threshold": 0.5,
                                                    "num_samples": 41,
                                                    "removed_features": [],
                                                    "left": {
                                                        "node_id": 59,
                                                        "feature_index": null,
                                                        "threshold": null,
                                                        "num_samples": 28,
                                                        "removed_features": [],
                                                        "left": null,
                                                        "right": null,
                                                        "output": 5,
                                                        "depth": 12
                                                    },
                                                    "right": {
                                                        "node_id": 58,
                                                        "feature_index": null,
                                                        "threshold": null,
                                                        "num_samples": 13,
                                                        "removed_features": [],
                                                        "left": null,
                                                        "right": null,
                                                        "output": 6,
                                                        "depth": 12
                                                    },
                                                    "output": null,
                                                    "depth": 11
                                                },
                                                "output": null,
                                                "depth": 10
                                            },
                                            "right": {
                                                "node_id": 39,
                                                "feature_index": 7,
                                                "threshold": 0.5,
                                                "num_samples": 86,
                                                "removed_features": [],
                                                "left": {
                                                    "node_id": 47,
                                                    "feature_index": 1,
                                                    "threshold": 0.5,
                                                    "num_samples": 56,
                                                    "removed_features": [],
                                                    "left": {
                                                        "node_id": 55,
                                                        "feature_index": null,
                                                        "threshold": null,
                                                        "num_samples": 18,
                                                        "removed_features": [],
                                                        "left": null,
                                                        "right": null,
                                                        "output": 1,
                                                        "depth": 12
                                                    },
                                                    "right": {
                                                        "node_id": 48,
                                                        "feature_index": 41,
                                                        "threshold": 0.5,
                                                        "num_samples": 38,
                                                        "removed_features": [],
                                                        "left": {
                                                            "node_id": 52,
                                                            "feature_index": 39,
                                                            "threshold": 0.5,
                                                            "num_samples": 16,
                                                            "removed_features": [],
                                                            "left": {
                                                                "node_id": 54,
                                                                "feature_index": null,
                                                                "threshold": null,
                                                                "num_samples": 5,
                                                                "removed_features": [],
                                                                "left": null,
                                                                "right": null,
                                                                "output": 11,
                                                                "depth": 14
                                                            },
                                                            "right": {
                                                                "node_id": 53,
                                                                "feature_index": null,
                                                                "threshold": null,
                                                                "num_samples": 11,
                                                                "removed_features": [],
                                                                "left": null,
                                                                "right": null,
                                                                "output": 3,
                                                                "depth": 14
                                                            },
                                                            "output": null,
                                                            "depth": 13
                                                        },
                                                        "right": {
                                                            "node_id": 49,
                                                            "feature_index": 39,
                                                            "threshold": 0.5,
                                                            "num_samples": 22,
                                                            "removed_features": [],
                                                            "left": {
                                                                "node_id": 51,
                                                                "feature_index": null,
                                                                "threshold": null,
                                                                "num_samples": 9,
                                                                "removed_features": [],
                                                                "left": null,
                                                                "right": null,
                                                                "output": 6,
                                                                "depth": 14
                                                            },
                                                            "right": {
                                                                "node_id": 50,
                                                                "feature_index": null,
                                                                "threshold": null,
                                                                "num_samples": 13,
                                                                "removed_features": [],
                                                                "left": null,
                                                                "right": null,
                                                                "output": 1,
                                                                "depth": 14
                                                            },
                                                            "output": null,
                                                            "depth": 13
                                                        },
                                                        "output": null,
                                                        "depth": 12
                                                    },
                                                    "output": null,
                                                    "depth": 11
                                                },
                                                "right": {
                                                    "node_id": 40,
                                                    "feature_index": 39,
                                                    "threshold": 0.5,
                                                    "num_samples": 30,
                                                    "removed_features": [],
                                                    "left": {
                                                        "node_id": 44,
                                                        "feature_index": 41,
                                                        "threshold": 0.5,
                                                        "num_samples": 20,
                                                        "removed_features": [],
                                                        "left": {
                                                            "node_id": 46,
                                                            "feature_index": null,
                                                            "threshold": null,
                                                            "num_samples": 1,
                                                            "removed_features": [],
                                                            "left": null,
                                                            "right": null,
                                                            "output": 11,
                                                            "depth": 13
                                                        },
                                                        "right": {
                                                            "node_id": 45,
                                                            "feature_index": null,
                                                            "threshold": null,
                                                            "num_samples": 19,
                                                            "removed_features": [],
                                                            "left": null,
                                                            "right": null,
                                                            "output": 10,
                                                            "depth": 13
                                                        },
                                                        "output": null,
                                                        "depth": 12
                                                    },
                                                    "right": {
                                                        "node_id": 41,
                                                        "feature_index": 15,
                                                        "threshold": 0.5,
                                                        "num_samples": 10,
                                                        "removed_features": [],
                                                        "left": {
                                                            "node_id": 43,
                                                            "feature_index": null,
                                                            "threshold": null,
                                                            "num_samples": 1,
                                                            "removed_features": [],
                                                            "left": null,
                                                            "right": null,
                                                            "output": 4,
                                                            "depth": 13
                                                        },
                                                        "right": {
                                                            "node_id": 42,
                                                            "feature_index": null,
                                                            "threshold": null,
                                                            "num_samples": 9,
                                                            "removed_features": [],
                                                            "left": null,
                                                            "right": null,
                                                            "output": 2,
                                                            "depth": 13
                                                        },
                                                        "output": null,
                                                        "depth": 12
                                                    },
                                                    "output": null,
                                                    "depth": 11
                                                },
                                                "output": null,
                                                "depth": 10
                                            },
                                            "output": null,
                                            "depth": 9
                                        },
                                        "right": {
                                            "node_id": 37,
                                            "feature_index": null,
                                            "threshold": null,
                                            "num_samples": 2006,
                                            "removed_features": [],
                                            "left": null,
                                            "right": null,
                                            "output": 1,
                                            "depth": 9
                                        },
                                        "output": null,
                                        "depth": 8
                                    },
                                    "right": {
                                        "node_id": 35,
                                        "feature_index": null,
                                        "threshold": null,
                                        "num_samples": 2109,
                                        "removed_features": [],
                                        "left": null,
                                        "right": null,
                                        "output": 1,
                                        "depth": 8
                                    },
                                    "output": null,
                                    "depth": 7
                                },
                                "right": {
                                    "node_id": 33,
                                    "feature_index": null,
                                    "threshold": null,
                                    "num_samples": 2005,
                                    "removed_features": [],
                                    "left": null,
                                    "right": null,
                                    "output": 3,
                                    "depth": 7
                                },
                                "output": null,
                                "depth": 6
                            },
                            "right": {
                                "node_id": 17,
                                "feature_index": 41,
                                "threshold": 0.5,
                                "num_samples": 3962,
                                "removed_features": [],
                                "left": {
                                    "node_id": 27,
                                    "feature_index": 30,
                                    "threshold": 0.5,
                                    "num_samples": 1918,
                                    "removed_features": [],
                                    "left": {
                                        "node_id": 29,
                                        "feature_index": 33,
                                        "threshold": 0.5,
                                        "num_samples": 1916,
                                        "removed_features": [],
                                        "left": {
                                            "node_id": 31,
                                            "feature_index": null,
                                            "threshold": null,
                                            "num_samples": 1914,
                                            "removed_features": [],
                                            "left": null,
                                            "right": null,
                                            "output": 5,
                                            "depth": 9
                                        },
                                        "right": {
                                            "node_id": 30,
                                            "feature_index": null,
                                            "threshold": null,
                                            "num_samples": 2,
                                            "removed_features": [],
                                            "left": null,
                                            "right": null,
                                            "output": 1,
                                            "depth": 9
                                        },
                                        "output": null,
                                        "depth": 8
                                    },
                                    "right": {
                                        "node_id": 28,
                                        "feature_index": null,
                                        "threshold": null,
                                        "num_samples": 2,
                                        "removed_features": [],
                                        "left": null,
                                        "right": null,
                                        "output": 1,
                                        "depth": 8
                                    },
                                    "output": null,
                                    "depth": 7
                                },
                                "right": {
                                    "node_id": 18,
                                    "feature_index": 32,
                                    "threshold": 0.5,
                                    "num_samples": 2044,
                                    "removed_features": [],
                                    "left": {
                                        "node_id": 20,
                                        "feature_index": 33,
                                        "threshold": 0.5,
                                        "num_samples": 2042,
                                        "removed_features": [],
                                        "left": {
                                            "node_id": 22,
                                            "feature_index": 36,
                                            "threshold": 0.5,
                                            "num_samples": 2040,
                                            "removed_features": [],
                                            "left": {
                                                "node_id": 24,
                                                "feature_index": 28,
                                                "threshold": 0.5,
                                                "num_samples": 2038,
                                                "removed_features": [],
                                                "left": {
                                                    "node_id": 26,
                                                    "feature_index": null,
                                                    "threshold": null,
                                                    "num_samples": 2037,
                                                    "removed_features": [],
                                                    "left": null,
                                                    "right": null,
                                                    "output": 6,
                                                    "depth": 11
                                                },
                                                "right": {
                                                    "node_id": 25,
                                                    "feature_index": null,
                                                    "threshold": null,
                                                    "num_samples": 1,
                                                    "removed_features": [],
                                                    "left": null,
                                                    "right": null,
                                                    "output": 4,
                                                    "depth": 11
                                                },
                                                "output": null,
                                                "depth": 10
                                            },
                                            "right": {
                                                "node_id": 23,
                                                "feature_index": null,
                                                "threshold": null,
                                                "num_samples": 2,
                                                "removed_features": [],
                                                "left": null,
                                                "right": null,
                                                "output": 4,
                                                "depth": 10
                                            },
                                            "output": null,
                                            "depth": 9
                                        },
                                        "right": {
                                            "node_id": 21,
                                            "feature_index": null,
                                            "threshold": null,
                                            "num_samples": 2,
                                            "removed_features": [],
                                            "left": null,
                                            "right": null,
                                            "output": 1,
                                            "depth": 9
                                        },
                                        "output": null,
                                        "depth": 8
                                    },
                                    "right": {
                                        "node_id": 19,
                                        "feature_index": null,
                                        "threshold": null,
                                        "num_samples": 2,
                                        "removed_features": [],
                                        "left": null,
                                        "right": null,
                                        "output": 3,
                                        "depth": 8
                                    },
                                    "output": null,
                                    "depth": 7
                                },
                                "output": null,
                                "depth": 6
                            },
                            "output": null,
                            "depth": 5
                        },
                        "right": {
                            "node_id": 13,
                            "feature_index": 39,
                            "threshold": 0.5,
                            "num_samples": 4028,
                            "removed_features": [],
                            "left": {
                                "node_id": 15,
                                "feature_index": null,
                                "threshold": null,
                                "num_samples": 2813,
                                "removed_features": [],
                                "left": null,
                                "right": null,
                                "output": 8,
                                "depth": 6
                            },
                            "right": {
                                "node_id": 14,
                                "feature_index": null,
                                "threshold": null,
                                "num_samples": 1215,
                                "removed_features": [],
                                "left": null,
                                "right": null,
                                "output": 7,
                                "depth": 6
                            },
                            "output": null,
                            "depth": 5
                        },
                        "output": null,
                        "depth": 4
                    },
                    "right": {
                        "node_id": 7,
                        "feature_index": 39,
                        "threshold": 0.5,
                        "num_samples": 7931,
                        "removed_features": [],
                        "left": {
                            "node_id": 11,
                            "feature_index": null,
                            "threshold": null,
                            "num_samples": 3923,
                            "removed_features": [],
                            "left": null,
                            "right": null,
                            "output": 2,
                            "depth": 5
                        },
                        "right": {
                            "node_id": 8,
                            "feature_index": 5,
                            "threshold": 0.5,
                            "num_samples": 4008,
                            "removed_features": [],
                            "left": {
                                "node_id": 10,
                                "feature_index": null,
                                "threshold": null,
                                "num_samples": 4004,
                                "removed_features": [],
                                "left": null,
                                "right": null,
                                "output": 9,
                                "depth": 6
                            },
                            "right": {
                                "node_id": 9,
                                "feature_index": null,
                                "threshold": null,
                                "num_samples": 4,
                                "removed_features": [],
                                "left": null,
                                "right": null,
                                "output": 2,
                                "depth": 6
                            },
                            "output": null,
                            "depth": 5
                        },
                        "output": null,
                        "depth": 4
                    },
                    "output": null,
                    "depth": 3
                },
                "right": {
                    "node_id": 5,
                    "feature_index": null,
                    "threshold": null,
                    "num_samples": 7965,
                    "removed_features": [],
                    "left": null,
                    "right": null,
                    "output": 0,
                    "depth": 3
                },
                "output": null,
                "depth": 2
            },
            "right": {
                "node_id": 3,
                "feature_index": null,
                "threshold": null,
                "num_samples": 8026,
                "removed_features": [],
                "left": null,
                "right": null,
                "output": 11,
                "depth": 2
            },
            "output": null,
            "depth": 1
        },
        "right": {
            "node_id": 1,
            "feature_index": null,
            "threshold": null,
            "num_samples": 8060,
            "removed_features": [],
            "left": null,
            "right": null,
            "output": 10,
            "depth": 1
        },
        "output": null,
        "depth": 0
    },
    "max_depth": null,
    "id_counter": 65,
    "feature_names": [
        "-3. Event = <PAD>",
        "-3. Event = asses eligibility",
        "-3. Event = bill patient",
        "-3. Event = collect history",
        "-3. Event = discuss options",
        "-3. Event = end",
        "-3. Event = explain diagnosis",
        "-3. Event = inform prevention",
        "-3. Event = mammary screening",
        "-3. Event = prostate screening",
        "-3. Event = refuse screening",
        "-3. Event = register",
        "-3. Event = start",
        "-2. Event = <PAD>",
        "-2. Event = asses eligibility",
        "-2. Event = bill patient",
        "-2. Event = collect history",
        "-2. Event = discuss options",
        "-2. Event = end",
        "-2. Event = explain diagnosis",
        "-2. Event = inform prevention",
        "-2. Event = mammary screening",
        "-2. Event = prostate screening",
        "-2. Event = refuse screening",
        "-2. Event = register",
        "-2. Event = start",
        "-1. Event = <PAD>",
        "-1. Event = asses eligibility",
        "-1. Event = bill patient",
        "-1. Event = collect history",
        "-1. Event = discuss options",
        "-1. Event = end",
        "-1. Event = explain diagnosis",
        "-1. Event = inform prevention",
        "-1. Event = mammary screening",
        "-1. Event = prostate screening",
        "-1. Event = refuse screening",
        "-1. Event = register",
        "-1. Event = start",
        "Attribute gender = female",
        "Attribute gender = male",
        "Attribute problems = false",
        "Attribute problems = true"
    ],
    "feature_indices": {
        "gender": [
            39,
            40
        ],
        "problems": [
            41,
            42
        ]
    },
    "class_names": [
        "asses eligibility",
        "bill patient",
        "collect history",
        "discuss options",
        "end",
        "explain diagnosis",
        "inform prevention",
        "mammary screening",
        "prostate screening",
        "refuse screening",
        "register",
        "start"
    ]
}